geventkafka/__init__.py
geventkafka/bstruct.py
geventkafka/client.py
geventkafka/conn.py
geventkafka/define.py
geventkafka/gevent_patch.py
geventkafka/protocol.py
geventkafka/tornado_patch.py
geventkafka/util.py
geventkafka-0.5.0.dist-info/LICENSE
geventkafka-0.5.0.dist-info/METADATA
geventkafka-0.5.0.dist-info/WHEEL
geventkafka-0.5.0.dist-info/top_level.txt
geventkafka-0.5.0.dist-info/RECORD
